drop/__init__.py
drop/defaults.cfg
drop/drop.py
drop-0.1.2.dist-info/DESCRIPTION.rst
drop-0.1.2.dist-info/entry_points.txt
drop-0.1.2.dist-info/METADATA
drop-0.1.2.dist-info/metadata.json
drop-0.1.2.dist-info/RECORD
drop-0.1.2.dist-info/top_level.txt
drop-0.1.2.dist-info/WHEEL
